README.md
setup.py
src/slime/__init__.py
src/slime.egg-info/PKG-INFO
src/slime.egg-info/SOURCES.txt
src/slime.egg-info/dependency_links.txt
src/slime.egg-info/not-zip-safe
src/slime.egg-info/requires.txt
src/slime.egg-info/top_level.txt
src/slime/core/__init__.py
src/slime/core/data.py
src/slime/core/utils.py
src/slime/model/__init__.py
src/slime/model/cov_model.py
src/slime/model/model.py