Metadata-Version: 1.0
Name: slime
Version: 0.0.0
Summary: Simple linear mixed effects modelwith priors and constraints.
Home-page: https://github.com/zhengp0/SLIME
Author: UNKNOWN
Author-email: UNKNOWN
License: MIT
Platform: UNKNOWN
